{
  "create": "Oluştur",
  "createSubheading": "Haritanızla bir uygulama oluşturun",
  "mapViewer": "Map Viewer",
  "mapViewerDesc": "Verileri keşfedin ve etkileşimli ve etkili web haritalarına dönüştürün.",
  "mapViewerDesc_archive": "Web haritaları oluşturmak, keşfetmek ve kaydetmek için etkileşimli bir web haritalama uygulamasıdır.",
  "arcgisStoryMaps": "ArcGIS StoryMaps",
  "storyMaps": "Story Maps",
  "storyMapsDesc": "Haritaları anlatı metinleri ve medya içerikleri ile birleştirerek bir hikaye anlatın.",
  "instantApps": "Instant Apps",
  "instantAppsDesc": "Haritanızı kullanarak odaklanmış bir deneyim sağlamak için bir uygulama seçin.",
  "dashboards": "Dashboards",
  "dashboardsDesc": "Temel bilgiler sağlayan veri görselleştirmeleri içeren bir kontrol paneli oluşturun.",
  "experienceBuilder": "Experience Builder",
  "experienceBuilderDesc": "Bir şablon kullanın veya istediğiniz tam web deneyimini oluşturmak için sıfırdan başlayın."
}