{
  "create": "Izveidot",
  "createSubheading": "Lietotnes izveide ar karti",
  "mapViewer": "Map Viewer",
  "mapViewerDesc": "Izpētiet un pārveidojiet datus interaktīvās un iespaidīgās tīmekļa kartēs.",
  "mapViewerDesc_archive": "Interaktīva tīmekļa kartēšanas lietotne tīmekļa karšu izveidei, izpētei un saglabāšanai.",
  "arcgisStoryMaps": "ArcGIS StoryMaps",
  "storyMaps": "Story Maps",
  "storyMapsDesc": "Izveidojiet stāstu, apvienojot kartes ar papildinošu tekstu un multividi.",
  "instantApps": "Instant Apps",
  "instantAppsDesc": "Izvēlieties piemērotāko lietotnes veidu savas kartes attēlošanai un izmantošanai.",
  "dashboards": "Informācijas paneļi",
  "dashboardsDesc": "Izveidojiet informācijas paneli ar datu vizualizācijām, kas sniedz būtiskus ieskatus.",
  "experienceBuilder": "Experience Builder",
  "experienceBuilderDesc": "Izmantojiet veidni vai sāciet veidot to no nulles, lai izveidotu nepieciešamo lietotni."
}