{
  "create": "한_Create_____________빠",
  "createSubheading": "한_Create an app with your map____________________________빠",
  "mapViewer": "한_Map Viewer_____________________빠",
  "mapViewerDesc": "한_Explore and transform data into interactive and impactful web maps___________________________________빠.",
  "mapViewerDesc_archive": "한_An interactive web mapping application for creating, exploring, and saving web maps___________________________________________빠.",
  "arcgisStoryMaps": "한_ArcGIS StoryMaps_________________빠",
  "storyMaps": "한_Story Maps_____________________빠",
  "storyMapsDesc": "한_Tell a story by combining maps with narrative text and media________________________________빠.",
  "instantApps": "한_Instant Apps_____________빠",
  "instantAppsDesc": "한_Choose an app to provide a focused experience using your map________________________________빠.",
  "dashboards": "한_Dashboards_____________________빠",
  "dashboardsDesc": "한_Create a dashboard with data visualizations that provide key insights____________________________________빠.",
  "experienceBuilder": "한_Experience Builder___________________빠",
  "experienceBuilderDesc": "한_Use a template or start from scratch to create the exact web experience you want__________________________________________빠."
}